table_categorization_agent/__init__.py
table_categorization_agent/agent.py
table_categorization_agent/cli.py
table_categorization_agent/config.py
table_categorization_agent/constants.py
table_categorization_agent/models.py
table_categorization_agent-0.1.3.dist-info/METADATA
table_categorization_agent-0.1.3.dist-info/WHEEL
table_categorization_agent-0.1.3.dist-info/entry_points.txt
table_categorization_agent-0.1.3.dist-info/top_level.txt
table_categorization_agent-0.1.3.dist-info/RECORD
