Metadata-Version: 2.4
Name: table-categorization-agent
Version: 0.1.3
Summary: LLM-driven agent for categorizing data tables based on domain schemas
Author-email: StepFn AI <rajesh@stepfunction.ai>
License-Expression: MIT
Project-URL: Homepage, https://github.com/stepfnAI/table-categorization-agent
Project-URL: Repository, https://github.com/stepfnAI/table-categorization-agent
Project-URL: Issues, https://github.com/stepfnAI/table-categorization-agent/issues
Classifier: Development Status :: 3 - Alpha
Classifier: Intended Audience :: Developers
Classifier: Intended Audience :: Science/Research
Classifier: Programming Language :: Python :: 3
Classifier: Programming Language :: Python :: 3.10
Classifier: Programming Language :: Python :: 3.11
Classifier: Programming Language :: Python :: 3.12
Classifier: Programming Language :: Python :: 3.13
Classifier: Topic :: Scientific/Engineering :: Artificial Intelligence
Classifier: Topic :: Scientific/Engineering :: Information Analysis
Requires-Python: >=3.10
Requires-Dist: sfn-blueprint>=0.6.6
Requires-Dist: pandas
Requires-Dist: pydantic-settings
Provides-Extra: dev
Requires-Dist: pytest>=7.0.0; extra == "dev"
Requires-Dist: pytest-cov>=4.0.0; extra == "dev"
Requires-Dist: black>=23.0.0; extra == "dev"
Requires-Dist: flake8>=6.0.0; extra == "dev"
Requires-Dist: mypy>=1.0.0; extra == "dev"
